odoo/addons/storage_backend_s3/README.rst
odoo/addons/storage_backend_s3/__init__.py
odoo/addons/storage_backend_s3/__manifest__.py
odoo/addons/storage_backend_s3/regions.py
odoo/addons/storage_backend_s3/components/__init__.py
odoo/addons/storage_backend_s3/components/s3_adapter.py
odoo/addons/storage_backend_s3/i18n/it.po
odoo/addons/storage_backend_s3/i18n/storage_backend_s3.pot
odoo/addons/storage_backend_s3/models/__init__.py
odoo/addons/storage_backend_s3/models/storage_backend.py
odoo/addons/storage_backend_s3/readme/CONFIGURE.md
odoo/addons/storage_backend_s3/readme/CONTRIBUTORS.md
odoo/addons/storage_backend_s3/readme/CREDITS.md
odoo/addons/storage_backend_s3/readme/DESCRIPTION.md
odoo/addons/storage_backend_s3/readme/ROADMAP.md
odoo/addons/storage_backend_s3/static/description/icon.png
odoo/addons/storage_backend_s3/static/description/index.html
odoo/addons/storage_backend_s3/tests/__init__.py
odoo/addons/storage_backend_s3/tests/test_amazon_s3.py
odoo/addons/storage_backend_s3/tests/cassettes/AmazonS3Case.test_setting_and_getting_data_from_dir.yaml
odoo/addons/storage_backend_s3/tests/cassettes/AmazonS3Case.test_setting_and_getting_data_from_root.yaml
odoo/addons/storage_backend_s3/views/backend_storage_view.xml
odoo_addon_storage_backend_s3-18.0.1.1.0.dist-info/METADATA
odoo_addon_storage_backend_s3-18.0.1.1.0.dist-info/WHEEL
odoo_addon_storage_backend_s3-18.0.1.1.0.dist-info/top_level.txt
odoo_addon_storage_backend_s3-18.0.1.1.0.dist-info/RECORD
