Metadata-Version: 2.1
Name: odoo-addon-storage_backend_s3
Version: 18.0.1.1.0
Requires-Python: >=3.10
Requires-Dist: boto3
Requires-Dist: odoo-addon-storage_backend==18.0.*
Requires-Dist: odoo==18.0.*
Summary: Implement amazon S3 Storage
Home-page: https://github.com/OCA/storage
License: LGPL-3
Author: Akretion, Odoo Community Association (OCA)
Author-email: support@odoo-community.org
Classifier: Programming Language :: Python
Classifier: Framework :: Odoo
Classifier: Framework :: Odoo :: 18.0
Classifier: License :: OSI Approved :: GNU Lesser General Public License v3 (LGPLv3)
